noronha/__init__.py
noronha/api/__init__.py
noronha/api/bvers.py
noronha/api/depl.py
noronha/api/ds.py
noronha/api/island.py
noronha/api/main.py
noronha/api/model.py
noronha/api/movers.py
noronha/api/note.py
noronha/api/proj.py
noronha/api/tchest.py
noronha/api/train.py
noronha/api/utils.py
noronha/bay/__init__.py
noronha/bay/anchor.py
noronha/bay/barrel.py
noronha/bay/captain.py
noronha/bay/cargo.py
noronha/bay/compass.py
noronha/bay/expedition.py
noronha/bay/goods.py
noronha/bay/island.py
noronha/bay/shipyard.py
noronha/bay/tchest.py
noronha/bay/trader.py
noronha/bay/utils.py
noronha/bay/warehouse.py
noronha/cli/__init__.py
noronha/cli/bvers.py
noronha/cli/callback.py
noronha/cli/depl.py
noronha/cli/ds.py
noronha/cli/handler.py
noronha/cli/isle.py
noronha/cli/main.py
noronha/cli/model.py
noronha/cli/movers.py
noronha/cli/note.py
noronha/cli/proj.py
noronha/cli/tchest.py
noronha/cli/train.py
noronha/common/__init__.py
noronha/common/annotations.py
noronha/common/conf.py
noronha/common/constants.py
noronha/common/errors.py
noronha/common/logging.py
noronha/common/parser.py
noronha/common/utils.py
noronha/db/__init__.py
noronha/db/bvers.py
noronha/db/depl.py
noronha/db/ds.py
noronha/db/main.py
noronha/db/model.py
noronha/db/movers.py
noronha/db/proj.py
noronha/db/tchest.py
noronha/db/train.py
noronha/db/utils.py
noronha/resources/__init__.py
noronha/resources/entrypoint.sh
noronha/resources/nha.yaml
noronha/resources/isle/artif/Dockerfile
noronha/resources/isle/mongo/Dockerfile
noronha/resources/isle/nexus/Dockerfile
noronha/resources/isle/router/Dockerfile
noronha/resources/isle/router/package.json
noronha/resources/isle/router/router.js
noronha/tools/__init__.py
noronha/tools/main.py
noronha/tools/notebook.py
noronha/tools/publish.py
noronha/tools/serving.py
noronha/tools/shortcuts.py
noronha/tools/utils.py
noronha_dataops-1.6.8.dist-info/LICENSE
noronha_dataops-1.6.8.dist-info/METADATA
noronha_dataops-1.6.8.dist-info/WHEEL
noronha_dataops-1.6.8.dist-info/entry_points.txt
noronha_dataops-1.6.8.dist-info/top_level.txt
noronha_dataops-1.6.8.dist-info/RECORD
