Metadata-Version: 2.1
Name: noronha-dataops
Version: 1.6.8
Summary: DataOps for Machine Learning
Home-page: https://github.com/noronha-dataops/noronha
Author: Noronha Development Team
Author-email: noronha.mlops@everis.com
License: Apache-2.0
Platform: Unix
Classifier: Development Status :: 4 - Beta
Classifier: Environment :: Console
Classifier: Intended Audience :: Developers
Classifier: Intended Audience :: Science/Research
Classifier: License :: OSI Approved :: Apache Software License
Classifier: Operating System :: Unix
Classifier: Programming Language :: Python :: 3
Classifier: Topic :: Scientific/Engineering :: Artificial Intelligence
Classifier: Topic :: Software Development :: Libraries :: Application Frameworks
License-File: LICENSE
Requires-Dist: pyvalid (==0.9.2)
Requires-Dist: kaptan
Requires-Dist: mongoengine
Requires-Dist: artifactory
Requires-Dist: nexus3-cli (==1.0.2)
Requires-Dist: random-name
Requires-Dist: gitpython
Requires-Dist: blinker
Requires-Dist: docker
Requires-Dist: click
Requires-Dist: conu
Requires-Dist: pyOpenSSL
Requires-Dist: keyring
Requires-Dist: keyring-jeepney
Requires-Dist: cassandra-driver (==3.21.0)
Requires-Dist: nbconvert (==5.6.1)
Requires-Dist: requests
Requires-Dist: kubernetes (==12.0.1)
